fui/__init__.py
fui/app.py
fui/auth/__init__.py
fui/auth/authorization.py
fui/auth/group.py
fui/auth/oauth_provider.py
fui/auth/oauth_token.py
fui/auth/providers/__init__.py
fui/auth/providers/auth0_oauth_provider.py
fui/auth/providers/azure_oauth_provider.py
fui/auth/providers/github_oauth_provider.py
fui/auth/providers/google_oauth_provider.py
fui/auth/user.py
fui/cli.py
fui/core/adaptive_control.py
fui/core/ads/banner.py
fui/core/ads/base_ad.py
fui/core/ads/interstitial.py
fui/core/ads/native.py
fui/core/alert_dialog.py
fui/core/alignment.py
fui/core/animated_switcher.py
fui/core/animation.py
fui/core/app_bar.py
fui/core/audio.py
fui/core/audio_recorder.py
fui/core/auto_complete.py
fui/core/autofill_group.py
fui/core/badge.py
fui/core/banner.py
fui/core/blur.py
fui/core/border.py
fui/core/border_radius.py
fui/core/bottom_app_bar.py
fui/core/bottom_sheet.py
fui/core/box.py
fui/core/button.py
fui/core/buttons.py
fui/core/camera.py
fui/core/canvas/arc.py
fui/core/canvas/canvas.py
fui/core/canvas/circle.py
fui/core/canvas/color.py
fui/core/canvas/fill.py
fui/core/canvas/line.py
fui/core/canvas/oval.py
fui/core/canvas/path.py
fui/core/canvas/points.py
fui/core/canvas/rect.py
fui/core/canvas/shadow.py
fui/core/canvas/shape.py
fui/core/canvas/text.py
fui/core/card.py
fui/core/charts/bar_chart.py
fui/core/charts/bar_chart_group.py
fui/core/charts/bar_chart_rod.py
fui/core/charts/bar_chart_rod_stack_item.py
fui/core/charts/chart_axis.py
fui/core/charts/chart_axis_label.py
fui/core/charts/chart_grid_lines.py
fui/core/charts/chart_point_line.py
fui/core/charts/chart_point_shape.py
fui/core/charts/line_chart.py
fui/core/charts/line_chart_data.py
fui/core/charts/line_chart_data_point.py
fui/core/charts/pie_chart.py
fui/core/charts/pie_chart_section.py
fui/core/checkbox.py
fui/core/chip.py
fui/core/circle_avatar.py
fui/core/client_storage.py
fui/core/colors.py
fui/core/column.py
fui/core/connection.py
fui/core/constrained_control.py
fui/core/container.py
fui/core/control.py
fuirc-1.0.0.dist-info/entry_points.txt
fuirc-1.0.0.dist-info/METADATA
fuirc-1.0.0.dist-info/WHEEL
fuirc-1.0.0.dist-info/RECORD
