Metadata-Version: 2.3
Name: Fuirc
Version: 1.0.0
Summary: fui for Python - easily build interactive multi-platform apps in Python
License: Apache-2.0
Author: Appveyor Systems Inc.
Author-email: hello@fui.dev
Requires-Python: >=3.8,<4.0
Classifier: License :: OSI Approved :: Apache Software License
Classifier: Programming Language :: Python :: 3
Classifier: Programming Language :: Python :: 3.8
Classifier: Programming Language :: Python :: 3.9
Classifier: Programming Language :: Python :: 3.10
Classifier: Programming Language :: Python :: 3.11
Classifier: Programming Language :: Python :: 3.12
Classifier: Programming Language :: Python :: 3.13
Provides-Extra: all
Provides-Extra: cli
Provides-Extra: desktop
Provides-Extra: web
Requires-Dist: fui-cli (==1.0.0) ; extra == "all" or extra == "cli"
Requires-Dist: fui-desktop (==1.0.0) ; (platform_system == "Darwin" or platform_system == "Windows") and (extra == "all" or extra == "desktop")
Requires-Dist: fui-web (==1.0.0) ; extra == "all" or extra == "web"
Requires-Dist: httpx ; platform_system != "Pyodide"
Requires-Dist: oauthlib (>=3.2.2,<4.0.0) ; platform_system != "Pyodide"
Requires-Dist: repath (>=0.9.0,<0.10.0)
Project-URL: documentation, https://fui.dev/docs
Project-URL: homepage, https://fui.dev
Project-URL: repository, https://github.com/fui-dev/fui
